cktgym_discovery_shared/__init__.py
cktgym_discovery_shared/dataclasses.py
cktgym_discovery_shared/git.py
cktgym_discovery_shared/rpc.py
cktgym_discovery_shared/user.py
cktgym_discovery_shared/Parameters/__init__.py
cktgym_discovery_shared/Parameters/parameters.py
cktgym_discovery_shared/Parameters/parameters_test.py
cktgym_discovery_shared/Results/__init__.py
cktgym_discovery_shared/Results/results.py
cktgym_discovery_shared/auth/__init__.py
cktgym_discovery_shared/mock/__init__.py
cktgym_discovery_shared/types/__init__.py
discovery_shared/__init__.py
discovery_shared/dataclasses.py
discovery_shared/git.py
discovery_shared/rpc.py
discovery_shared/user.py
discovery_shared/Parameters/__init__.py
discovery_shared/Parameters/parameters.py
discovery_shared/Parameters/parameters_test.py
discovery_shared/Results/__init__.py
discovery_shared/Results/results.py
discovery_shared/auth/__init__.py
discovery_shared/mock/__init__.py
discovery_shared/types/__init__.py
cktgym_discovery_shared-0.0.4.dist-info/METADATA
cktgym_discovery_shared-0.0.4.dist-info/WHEEL
cktgym_discovery_shared-0.0.4.dist-info/top_level.txt
cktgym_discovery_shared-0.0.4.dist-info/RECORD
