Metadata-Version: 2.1
Name: cktgym-discovery-shared
Version: 0.0.4
Summary: BWRC AMS ML Discovery Shared
Home-page: https://github.com/BWRC-AMS-ML-Discovery
Author: The Regents of the University of California
Author-email: haohanw@eecs.berkeley.edu
License: UNKNOWN
Platform: UNKNOWN
Requires-Python: >=3.7, <3.11
Requires-Dist: GitPython (>=3.1.31)
Requires-Dist: pydantic (<1.11,>=1.9.0)
Provides-Extra: dev
Requires-Dist: pytest (==7.1) ; extra == 'dev'
Requires-Dist: coverage ; extra == 'dev'
Requires-Dist: pytest-cov ; extra == 'dev'
Requires-Dist: pre-commit (==2.20) ; extra == 'dev'
Requires-Dist: black (==22.6) ; extra == 'dev'
Requires-Dist: twine ; extra == 'dev'
